[
  {
    "link": "https://duckduckgo.com/",
    "logo": "/duckduckgo.svg",
    "title": "duckduckgo.com"
  },
  {
    "link": "https://deepl.com/",
    "logo": "/deepl.svg",
    "title": "deepl.com"
  },
  {
    "link": "https://www.perplexity.ai/",
    "logo": "/perplexity.svg",
    "title": "perplexity.ai"
  },
  {
    "link": "https://www.excalidraw.com/",
    "logo": "/excalidraw.svg",
    "title": "excalidraw.com"
  },
  {
    "link": "https://app.diagrams.net/",
    "logo": "/diagrams.svg",
    "title": "app.diagrams.net"
  },
  {
    "link": "https://www.figma.com/",
    "logo": "/figma.svg",
    "title": "figma.com"
  },
  {
    "link": "https://learnxinyminutes.com/",
    "logo": "/learnxinyminutes.svg",
    "title": "learnxinyminutes.com"
  }
]
